envpy/__init__.py
envpy/parser.py
envpy-0.1.0.dist-info/DESCRIPTION.rst
envpy-0.1.0.dist-info/METADATA
envpy-0.1.0.dist-info/RECORD
envpy-0.1.0.dist-info/WHEEL
envpy-0.1.0.dist-info/metadata.json
envpy-0.1.0.dist-info/top_level.txt
