Metadata-Version: 2.0
Name: envpy
Version: 0.1.0
Summary: Python library for loading config from environment variables.
Home-page: https://github.com/turingincomplete/envpy
Author: Jonathan Lloyd
Author-email: jonathan@thisisjonathan.com
License: UNKNOWN
Download-URL: https://github.com/turingincomplete/envpy/archive/v0.1.0.tar.gz
Platform: UNKNOWN
Classifier: Development Status :: 3 - Alpha
Classifier: Intended Audience :: Developers
Classifier: Programming Language :: Python :: 3
Requires-Python: >=3
